intflags.py
LICENSE
intflags-2.0.0.dist-info/LICENSE
intflags-2.0.0.dist-info/WHEEL
intflags-2.0.0.dist-info/METADATA
intflags-2.0.0.dist-info/RECORD
