Metadata-Version: 2.1
Name: intflags
Version: 2.0.0
Summary: The simplest way to create bit-flags
Home-page: https://github.com/SeparateRecords/intflags
License: ISC
Keywords: flags,bitflags
Author: SeparateRecords
Author-email: me@rob.ac
Requires-Python: >=3.0,<4.0
Classifier: Development Status :: 5 - Production/Stable
Classifier: Intended Audience :: Developers
Classifier: License :: OSI Approved
Classifier: License :: OSI Approved :: ISC License (ISCL)
Classifier: Programming Language :: Python :: 3
Classifier: Programming Language :: Python :: 3.4
Classifier: Programming Language :: Python :: 3.5
Classifier: Programming Language :: Python :: 3.6
Classifier: Programming Language :: Python :: 3.7
Classifier: Programming Language :: Python :: 3.8
Project-URL: Repository, https://github.com/SeparateRecords/intflags
